efficientnet_lite_pytorch/__init__.py
efficientnet_lite_pytorch/model.py
efficientnet_lite_pytorch/utils.py
efficientnet_lite_pytorch-0.1.0.dist-info/LICENSE
efficientnet_lite_pytorch-0.1.0.dist-info/METADATA
efficientnet_lite_pytorch-0.1.0.dist-info/WHEEL
efficientnet_lite_pytorch-0.1.0.dist-info/top_level.txt
efficientnet_lite_pytorch-0.1.0.dist-info/RECORD
