Metadata-Version: 2.1
Name: efficientnet-lite-pytorch
Version: 0.1.0
Summary: EfficientNet-Lite implemented in PyTorch.
Home-page: https://github.com/ml-illustrated/EfficientNet-Lite-PyTorch
Author: ML Illustrated
Author-email: gerald@ml-illustrated.com
License: Apache
Platform: UNKNOWN
Classifier: License :: OSI Approved :: Apache Software License
Classifier: Programming Language :: Python
Classifier: Programming Language :: Python :: 3
Classifier: Programming Language :: Python :: 3.6
Requires-Python: >=3.5.0
Requires-Dist: torch
